{"id":12,"count":35,"description":"","link":"http:\/\/ijz.me\/?cat=12","name":"\u7f16\u7a0b","slug":"program","taxonomy":"category","parent":0,"meta":[],"_links":{"self":[{"href":"http:\/\/ijz.me\/index.php?rest_route=\/wp\/v2\/categories\/12","targetHints":{"allow":["GET"]}}],"collection":[{"href":"http:\/\/ijz.me\/index.php?rest_route=\/wp\/v2\/categories"}],"about":[{"href":"http:\/\/ijz.me\/index.php?rest_route=\/wp\/v2\/taxonomies\/category"}],"wp:post_type":[{"href":"http:\/\/ijz.me\/index.php?rest_route=%2Fwp%2Fv2%2Fposts&categories=12"}],"curies":[{"name":"wp","href":"https:\/\/api.w.org\/{rel}","templated":true}]}}