{"id":105,"date":"2013-07-11T16:59:11","date_gmt":"2013-07-11T08:59:11","guid":{"rendered":"http:\/\/localhost\/?p=105"},"modified":"2013-07-11T16:59:11","modified_gmt":"2013-07-11T08:59:11","slug":"%e5%8c%97%e6%96%97%e6%98%9f%e4%bf%ae%e5%a5%bd%e4%ba%86%e3%80%82%e3%80%82","status":"publish","type":"post","link":"http:\/\/ijz.me\/?p=105","title":{"rendered":"\u5317\u6597\u661f\u4fee\u597d\u4e86\u3002\u3002"},"content":{"rendered":"<p>\u521a\u521a\u770b\u5230\u5317\u6597\u661f\u88ab\u4fee\u597d\u4e86\uff0c\u771f\u662f\u8d5e\u5440\uff01<\/p>\n<p>\u54b1\u4eec\u7684\u536b\u661f\u5de5\u4f5c\u8005\u5c31\u662f\u725b\uff0c\u80fd\u628a\u6b7b\u9a6c\u7ed9\u533b\u6d3b\u4e86\u3002<\/p>\n","protected":false},"excerpt":{"rendered":"<p>\u521a\u521a\u770b\u5230\u5317\u6597\u661f\u88ab\u4fee\u597d\u4e86\uff0c\u771f\u662f\u8d5e\u5440\uff01 \u54b1\u4eec\u7684\u536b\u661f\u5de5\u4f5c\u8005\u5c31\u662f\u725b\uff0c\u80fd\u628a\u6b7b\u9a6c\u7ed9\u533b\u6d3b\u4e86\u3002<\/p>\n","protected":false},"author":2,"featured_media":0,"comment_status":"open","ping_status":"open","sticky":false,"template":"","format":"standard","meta":{"footnotes":""},"categories":[17],"tags":[],"class_list":["post-105","post","type-post","status-publish","format-standard","hentry","category-sg"],"_links":{"self":[{"href":"http:\/\/ijz.me\/index.php?rest_route=\/wp\/v2\/posts\/105","targetHints":{"allow":["GET"]}}],"collection":[{"href":"http:\/\/ijz.me\/index.php?rest_route=\/wp\/v2\/posts"}],"about":[{"href":"http:\/\/ijz.me\/index.php?rest_route=\/wp\/v2\/types\/post"}],"author":[{"embeddable":true,"href":"http:\/\/ijz.me\/index.php?rest_route=\/wp\/v2\/users\/2"}],"replies":[{"embeddable":true,"href":"http:\/\/ijz.me\/index.php?rest_route=%2Fwp%2Fv2%2Fcomments&post=105"}],"version-history":[{"count":0,"href":"http:\/\/ijz.me\/index.php?rest_route=\/wp\/v2\/posts\/105\/revisions"}],"wp:attachment":[{"href":"http:\/\/ijz.me\/index.php?rest_route=%2Fwp%2Fv2%2Fmedia&parent=105"}],"wp:term":[{"taxonomy":"category","embeddable":true,"href":"http:\/\/ijz.me\/index.php?rest_route=%2Fwp%2Fv2%2Fcategories&post=105"},{"taxonomy":"post_tag","embeddable":true,"href":"http:\/\/ijz.me\/index.php?rest_route=%2Fwp%2Fv2%2Ftags&post=105"}],"curies":[{"name":"wp","href":"https:\/\/api.w.org\/{rel}","templated":true}]}}